botright/__init__.py
botright/botright.py
botright/extended_typing.py
botright/modules/__init__.py
botright/modules/faker.py
botright/modules/geetest.py
botright/modules/geetest.torchscript
botright/modules/geetest_helpers.py
botright/modules/hcaptcha.py
botright/modules/proxy_manager.py
botright/playwright_mock/__init__.py
botright/playwright_mock/browser.py
botright/playwright_mock/frame.py
botright/playwright_mock/frame_locator.py
botright/playwright_mock/handles.py
botright/playwright_mock/keyboard.py
botright/playwright_mock/locator.py
botright/playwright_mock/mouse.py
botright/playwright_mock/page.py
botright/playwright_mock/routes.py
botright-0.5.1.dist-info/LICENSE
botright-0.5.1.dist-info/METADATA
botright-0.5.1.dist-info/WHEEL
botright-0.5.1.dist-info/top_level.txt
botright-0.5.1.dist-info/RECORD
