Metadata-Version: 2.1
Name: botright
Version: 0.5.1
Summary: Botright, the most advance undetected, fingerprint-changing, captcha-solving, open-source automation framework. Build on Playwright, its as easy to use as it is to extend your code. Solving your Captchas for free with AI.
Home-page: https://github.com/Vinyzu/Botright
Author: Vinyzu
License: GNU General Public License v3.0
Project-URL: Source, https://github.com/Vinyzu/Botright
Project-URL: Documentation, https://github.com/Vinyzu/Botright/blob/main/docs/index.rst
Project-URL: Tracker, https://github.com/Vinyzu/Botright/issues
Keywords: botright,playwright,browser,automation,recaptcha_challenger,recaptcha-solver,hcaptcha_challenger,hcaptcha-solver,geetest_challenger,geetest-solver
Classifier: Topic :: Scientific/Engineering
Classifier: Topic :: Scientific/Engineering :: Artificial Intelligence
Classifier: Topic :: Software Development
Classifier: Topic :: Software Development :: Libraries
Classifier: Topic :: Software Development :: Libraries :: Python Modules
Classifier: Topic :: Internet :: WWW/HTTP :: Browsers
Classifier: License :: OSI Approved :: Apache Software License
Classifier: Programming Language :: Python :: 3
Requires-Python: >=3.8
License-File: LICENSE
Requires-Dist: async-class
Requires-Dist: httpx >=0.24.1
Requires-Dist: playwright >=1.40.0
Requires-Dist: undetected-playwright-patch
Requires-Dist: pybrowsers >=0.5.2
Requires-Dist: chrome-fingerprints
Requires-Dist: numpy
Requires-Dist: hcaptcha-challenger >=0.10.1.post1
Requires-Dist: recognizer
Requires-Dist: setuptools
Requires-Dist: loguru
Provides-Extra: testing
Requires-Dist: pytest ; extra == 'testing'
Requires-Dist: mypy ; extra == 'testing'
Requires-Dist: flake8 ; extra == 'testing'
Requires-Dist: black ; extra == 'testing'
Requires-Dist: isort ; extra == 'testing'
